PyWCSTools/__init__.py
PyWCSTools/_wcs.cpython-312-darwin.so
PyWCSTools/wcs.py
PyWCSTools/wcscon.py
astLib/__init__.py
astLib/astCalc.py
astLib/astCoords.py
astLib/astImages.py
astLib/astPlots.py
astLib/astSED.py
astLib/astStats.py
astLib/astWCS.py
astLib/data/bohlin2006_Vega.sed
astLib/data/sun_reference_stis_001.ascii
astLib-0.12.1.dist-info/LICENSE
astLib-0.12.1.dist-info/METADATA
astLib-0.12.1.dist-info/WHEEL
astLib-0.12.1.dist-info/top_level.txt
astLib-0.12.1.dist-info/RECORD
