Metadata-Version: 2.1
Name: astLib
Version: 0.12.1
Summary: A set of python modules for producing simple plots, statistics, common calculations, coordinate conversions, and manipulating FITS images with World Coordinate System (WCS) information
Home-page: https://astlib.readthedocs.io
Author: Matt Hilton & Steven Boada
Author-email: matt.hilton@mykolab.com
License: LGPL
Keywords: astrophysics,astronomy
Classifier: Programming Language :: Python :: 3
Classifier: Environment :: Console
Classifier: Intended Audience :: Science/Research
Classifier: License :: OSI Approved :: GNU Library or Lesser General Public License (LGPL)
Classifier: Natural Language :: English
Classifier: Operating System :: POSIX
Classifier: Topic :: Scientific/Engineering :: Astronomy
Classifier: Topic :: Software Development :: Libraries
License-File: LICENSE
Requires-Dist: astropy>=3.2
Requires-Dist: numpy<2,>=1.10
Requires-Dist: matplotlib>=3.0
Requires-Dist: scipy>=1.7
